colorls/__init__.py
colorls/cli.py
colorls/colorls.py
colorls-1.3.0.data/scripts/callls
colorls-1.3.0.data/scripts/calls
colorls-1.3.0.data/scripts/cals
colorls-1.3.0.data/scripts/cllls
colorls-1.3.0.data/scripts/clls
colorls-1.3.0.data/scripts/cls
colorls-1.3.0.data/scripts/csallls
colorls-1.3.0.data/scripts/csalls
colorls-1.3.0.data/scripts/csals
colorls-1.3.0.data/scripts/csllls
colorls-1.3.0.data/scripts/cslls
colorls-1.3.0.data/scripts/csls
colorls-1.3.0.dist-info/COPYING
colorls-1.3.0.dist-info/LICENSE
colorls-1.3.0.dist-info/METADATA
colorls-1.3.0.dist-info/WHEEL
colorls-1.3.0.dist-info/entry_points.txt
colorls-1.3.0.dist-info/top_level.txt
colorls-1.3.0.dist-info/RECORD
