Metadata-Version: 2.1
Name: colorls
Version: 1.3.0
Summary: c*ls commands that use colour and pipe output to less, with a sensible prompt
Home-page: https://github.com/unixnut/cls
Author: Alastair Irvine
Author-email: alastair@plug.org.au
License: GNU General Public License v2
Keywords: cls,ls,less,colour,color
Platform: UNKNOWN
Classifier: Development Status :: 4 - Beta
Classifier: Intended Audience :: End Users/Desktop
Classifier: Intended Audience :: System Administrators
Classifier: License :: OSI Approved :: GNU General Public License v2 (GPLv2)
Classifier: Environment :: Console
Classifier: Topic :: Utilities
Classifier: Operating System :: POSIX :: Linux
Classifier: Natural Language :: English
Classifier: Programming Language :: Python :: 3
Classifier: Programming Language :: Python :: 3.4
Classifier: Programming Language :: Python :: 3.5
Classifier: Programming Language :: Python :: 3.6
Classifier: Programming Language :: Python :: 3.7
Classifier: Programming Language :: Python :: 3.8
Classifier: Programming Language :: Unix Shell
Requires-Python: >=3.4
Requires-Dist: colored (~=1.4.3)
